<annotation>
	<folder>VOC2007</folder>
	<filename>e0534b9ba69a5a34.jpg</filename>
	<source>
		<database>OpenImagese</database>
		<annotation></annotation>
		<image></image>
		<flickrid></flickrid>
	</source>
	<owner>
		<flickrid></flickrid>
		<name></name>
	</owner>
	<size>
		<width>1024</width>
		<height>756</height>
		<depth>3</depth>
	</size>
	<segmented>0</segmented>
<object>
		<name>/m/07j7r</name>
		<truncated>1</truncated>
		<bndbox>
			<xmin>66</xmin>
			<ymin>28</ymin>
			<xmax>933</xmax>
			<ymax>546</ymax>
		</bndbox>
	</object>
<object>
		<name>/m/07j7r</name>
		<truncated>1</truncated>
		<bndbox>
			<xmin>22</xmin>
			<ymin>165</ymin>
			<xmax>72</xmax>
			<ymax>352</ymax>
		</bndbox>
	</object>
<object>
		<name>/m/07j7r</name>
		<truncated>0</truncated>
		<bndbox>
			<xmin>48</xmin>
			<ymin>67</ymin>
			<xmax>208</xmax>
			<ymax>173</ymax>
		</bndbox>
	</object>
<object>
		<name>/m/07j7r</name>
		<truncated>1</truncated>
		<bndbox>
			<xmin>646</xmin>
			<ymin>14</ymin>
			<xmax>1000</xmax>
			<ymax>479</ymax>
		</bndbox>
	</object>

</annotation>