<annotation>
	<folder>VOC2007</folder>
	<filename>e08e8bbe152bbdb2.jpg</filename>
	<source>
		<database>OpenImagese</database>
		<annotation></annotation>
		<image></image>
		<flickrid></flickrid>
	</source>
	<owner>
		<flickrid></flickrid>
		<name></name>
	</owner>
	<size>
		<width>1024</width>
		<height>768</height>
		<depth>3</depth>
	</size>
	<segmented>0</segmented>
<object>
		<name>/m/0cgh4</name>
		<truncated>1</truncated>
		<bndbox>
			<xmin>0</xmin>
			<ymin>120</ymin>
			<xmax>330</xmax>
			<ymax>767</ymax>
		</bndbox>
	</object>
<object>
		<name>/m/0cgh4</name>
		<truncated>1</truncated>
		<bndbox>
			<xmin>207</xmin>
			<ymin>1</ymin>
			<xmax>1023</xmax>
			<ymax>721</ymax>
		</bndbox>
	</object>
<object>
		<name>/m/0k4j</name>
		<truncated>1</truncated>
		<bndbox>
			<xmin>303</xmin>
			<ymin>681</ymin>
			<xmax>620</xmax>
			<ymax>767</ymax>
		</bndbox>
	</object>
<object>
		<name>/m/0k4j</name>
		<truncated>1</truncated>
		<bndbox>
			<xmin>857</xmin>
			<ymin>695</ymin>
			<xmax>1023</xmax>
			<ymax>762</ymax>
		</bndbox>
	</object>
<object>
		<name>/m/0k4j</name>
		<truncated>0</truncated>
		<bndbox>
			<xmin>864</xmin>
			<ymin>672</ymin>
			<xmax>990</xmax>
			<ymax>712</ymax>
		</bndbox>
	</object>
<object>
		<name>/m/0k4j</name>
		<truncated>1</truncated>
		<bndbox>
			<xmin>864</xmin>
			<ymin>728</ymin>
			<xmax>1023</xmax>
			<ymax>767</ymax>
		</bndbox>
	</object>
<object>
		<name>/m/0k4j</name>
		<truncated>1</truncated>
		<bndbox>
			<xmin>883</xmin>
			<ymin>686</ymin>
			<xmax>1017</xmax>
			<ymax>707</ymax>
		</bndbox>
	</object>

</annotation>