<annotation>
	<folder>VOC2007</folder>
	<filename>e13075877ebfdf78.jpg</filename>
	<source>
		<database>OpenImagese</database>
		<annotation></annotation>
		<image></image>
		<flickrid></flickrid>
	</source>
	<owner>
		<flickrid></flickrid>
		<name></name>
	</owner>
	<size>
		<width>1024</width>
		<height>683</height>
		<depth>3</depth>
	</size>
	<segmented>0</segmented>
<object>
		<name>/m/01g317</name>
		<truncated>1</truncated>
		<bndbox>
			<xmin>69</xmin>
			<ymin>73</ymin>
			<xmax>169</xmax>
			<ymax>403</ymax>
		</bndbox>
	</object>
<object>
		<name>/m/01g317</name>
		<truncated>0</truncated>
		<bndbox>
			<xmin>105</xmin>
			<ymin>265</ymin>
			<xmax>198</xmax>
			<ymax>481</ymax>
		</bndbox>
	</object>
<object>
		<name>/m/01g317</name>
		<truncated>0</truncated>
		<bndbox>
			<xmin>207</xmin>
			<ymin>245</ymin>
			<xmax>323</xmax>
			<ymax>493</ymax>
		</bndbox>
	</object>
<object>
		<name>/m/01g317</name>
		<truncated>0</truncated>
		<bndbox>
			<xmin>359</xmin>
			<ymin>151</ymin>
			<xmax>554</xmax>
			<ymax>637</ymax>
		</bndbox>
	</object>
<object>
		<name>/m/01g317</name>
		<truncated>0</truncated>
		<bndbox>
			<xmin>670</xmin>
			<ymin>204</ymin>
			<xmax>841</xmax>
			<ymax>540</ymax>
		</bndbox>
	</object>
<object>
		<name>/m/09j5n</name>
		<truncated>0</truncated>
		<bndbox>
			<xmin>108</xmin>
			<ymin>463</ymin>
			<xmax>147</xmax>
			<ymax>481</ymax>
		</bndbox>
	</object>
<object>
		<name>/m/09j5n</name>
		<truncated>0</truncated>
		<bndbox>
			<xmin>153</xmin>
			<ymin>469</ymin>
			<xmax>195</xmax>
			<ymax>483</ymax>
		</bndbox>
	</object>
<object>
		<name>/m/09j5n</name>
		<truncated>0</truncated>
		<bndbox>
			<xmin>210</xmin>
			<ymin>469</ymin>
			<xmax>252</xmax>
			<ymax>494</ymax>
		</bndbox>
	</object>
<object>
		<name>/m/09j5n</name>
		<truncated>0</truncated>
		<bndbox>
			<xmin>278</xmin>
			<ymin>464</ymin>
			<xmax>323</xmax>
			<ymax>481</ymax>
		</bndbox>
	</object>
<object>
		<name>/m/09j5n</name>
		<truncated>0</truncated>
		<bndbox>
			<xmin>473</xmin>
			<ymin>567</ymin>
			<xmax>542</xmax>
			<ymax>608</ymax>
		</bndbox>
	</object>
<object>
		<name>/m/09j5n</name>
		<truncated>0</truncated>
		<bndbox>
			<xmin>671</xmin>
			<ymin>470</ymin>
			<xmax>698</xmax>
			<ymax>531</ymax>
		</bndbox>
	</object>
<object>
		<name>/m/09j5n</name>
		<truncated>0</truncated>
		<bndbox>
			<xmin>777</xmin>
			<ymin>511</ymin>
			<xmax>833</xmax>
			<ymax>543</ymax>
		</bndbox>
	</object>

</annotation>