<annotation>
	<folder>VOC2007</folder>
	<filename>e135ae6f5e1fb40f.jpg</filename>
	<source>
		<database>OpenImagese</database>
		<annotation></annotation>
		<image></image>
		<flickrid></flickrid>
	</source>
	<owner>
		<flickrid></flickrid>
		<name></name>
	</owner>
	<size>
		<width>1024</width>
		<height>683</height>
		<depth>3</depth>
	</size>
	<segmented>0</segmented>
<object>
		<name>/m/01g317</name>
		<truncated>1</truncated>
		<bndbox>
			<xmin>352</xmin>
			<ymin>409</ymin>
			<xmax>490</xmax>
			<ymax>682</ymax>
		</bndbox>
	</object>
<object>
		<name>/m/01xyhv</name>
		<truncated>1</truncated>
		<bndbox>
			<xmin>367</xmin>
			<ymin>467</ymin>
			<xmax>487</xmax>
			<ymax>682</ymax>
		</bndbox>
	</object>
<object>
		<name>/m/0hg7b</name>
		<truncated>0</truncated>
		<bndbox>
			<xmin>323</xmin>
			<ymin>469</ymin>
			<xmax>359</xmax>
			<ymax>499</ymax>
		</bndbox>
	</object>

</annotation>