<annotation>
	<folder>VOC2007</folder>
	<filename>e1d9a6b46f9f44a2.jpg</filename>
	<source>
		<database>OpenImagese</database>
		<annotation></annotation>
		<image></image>
		<flickrid></flickrid>
	</source>
	<owner>
		<flickrid></flickrid>
		<name></name>
	</owner>
	<size>
		<width>1024</width>
		<height>1024</height>
		<depth>3</depth>
	</size>
	<segmented>0</segmented>
<object>
		<name>/m/04yx4</name>
		<truncated>1</truncated>
		<bndbox>
			<xmin>709</xmin>
			<ymin>331</ymin>
			<xmax>1020</xmax>
			<ymax>1024</ymax>
		</bndbox>
	</object>
<object>
		<name>/m/09j2d</name>
		<truncated>0</truncated>
		<bndbox>
			<xmin>483</xmin>
			<ymin>431</ymin>
			<xmax>660</xmax>
			<ymax>649</ymax>
		</bndbox>
	</object>
<object>
		<name>/m/01mzpv</name>
		<truncated>1</truncated>
		<bndbox>
			<xmin>0</xmin>
			<ymin>555</ymin>
			<xmax>40</xmax>
			<ymax>691</ymax>
		</bndbox>
	</object>
<object>
		<name>/m/01mzpv</name>
		<truncated>1</truncated>
		<bndbox>
			<xmin>88</xmin>
			<ymin>839</ymin>
			<xmax>349</xmax>
			<ymax>1022</ymax>
		</bndbox>
	</object>
<object>
		<name>/m/01mzpv</name>
		<truncated>0</truncated>
		<bndbox>
			<xmin>225</xmin>
			<ymin>512</ymin>
			<xmax>353</xmax>
			<ymax>680</ymax>
		</bndbox>
	</object>
<object>
		<name>/m/01mzpv</name>
		<truncated>0</truncated>
		<bndbox>
			<xmin>359</xmin>
			<ymin>483</ymin>
			<xmax>470</xmax>
			<ymax>627</ymax>
		</bndbox>
	</object>
<object>
		<name>/m/01mzpv</name>
		<truncated>0</truncated>
		<bndbox>
			<xmin>471</xmin>
			<ymin>470</ymin>
			<xmax>543</xmax>
			<ymax>585</ymax>
		</bndbox>
	</object>
<object>
		<name>/m/01mzpv</name>
		<truncated>0</truncated>
		<bndbox>
			<xmin>550</xmin>
			<ymin>542</ymin>
			<xmax>667</xmax>
			<ymax>714</ymax>
		</bndbox>
	</object>
<object>
		<name>/m/01mzpv</name>
		<truncated>0</truncated>
		<bndbox>
			<xmin>624</xmin>
			<ymin>580</ymin>
			<xmax>813</xmax>
			<ymax>891</ymax>
		</bndbox>
	</object>
<object>
		<name>/m/01mzpv</name>
		<truncated>0</truncated>
		<bndbox>
			<xmin>639</xmin>
			<ymin>491</ymin>
			<xmax>721</xmax>
			<ymax>625</ymax>
		</bndbox>
	</object>
<object>
		<name>/m/01mzpv</name>
		<truncated>0</truncated>
		<bndbox>
			<xmin>665</xmin>
			<ymin>506</ymin>
			<xmax>818</xmax>
			<ymax>675</ymax>
		</bndbox>
	</object>
<object>
		<name>/m/01mzpv</name>
		<truncated>0</truncated>
		<bndbox>
			<xmin>754</xmin>
			<ymin>421</ymin>
			<xmax>853</xmax>
			<ymax>555</ymax>
		</bndbox>
	</object>
<object>
		<name>/m/01mzpv</name>
		<truncated>1</truncated>
		<bndbox>
			<xmin>769</xmin>
			<ymin>649</ymin>
			<xmax>1022</xmax>
			<ymax>1022</ymax>
		</bndbox>
	</object>
<object>
		<name>/m/04yx4</name>
		<truncated>1</truncated>
		<bndbox>
			<xmin>0</xmin>
			<ymin>506</ymin>
			<xmax>167</xmax>
			<ymax>744</ymax>
		</bndbox>
	</object>
<object>
		<name>/m/04yx4</name>
		<truncated>0</truncated>
		<bndbox>
			<xmin>25</xmin>
			<ymin>445</ymin>
			<xmax>220</xmax>
			<ymax>642</ymax>
		</bndbox>
	</object>
<object>
		<name>/m/04yx4</name>
		<truncated>1</truncated>
		<bndbox>
			<xmin>162</xmin>
			<ymin>563</ymin>
			<xmax>630</xmax>
			<ymax>1022</ymax>
		</bndbox>
	</object>
<object>
		<name>/m/04yx4</name>
		<truncated>0</truncated>
		<bndbox>
			<xmin>503</xmin>
			<ymin>416</ymin>
			<xmax>669</xmax>
			<ymax>691</ymax>
		</bndbox>
	</object>
<object>
		<name>/m/04yx4</name>
		<truncated>0</truncated>
		<bndbox>
			<xmin>680</xmin>
			<ymin>287</ymin>
			<xmax>813</xmax>
			<ymax>604</ymax>
		</bndbox>
	</object>
<object>
		<name>/m/09j2d</name>
		<truncated>0</truncated>
		<bndbox>
			<xmin>11</xmin>
			<ymin>612</ymin>
			<xmax>108</xmax>
			<ymax>803</ymax>
		</bndbox>
	</object>
<object>
		<name>/m/09j2d</name>
		<truncated>0</truncated>
		<bndbox>
			<xmin>23</xmin>
			<ymin>518</ymin>
			<xmax>210</xmax>
			<ymax>650</ymax>
		</bndbox>
	</object>
<object>
		<name>/m/09j2d</name>
		<truncated>0</truncated>
		<bndbox>
			<xmin>28</xmin>
			<ymin>716</ymin>
			<xmax>337</xmax>
			<ymax>1008</ymax>
		</bndbox>
	</object>
<object>
		<name>/m/09j2d</name>
		<truncated>1</truncated>
		<bndbox>
			<xmin>112</xmin>
			<ymin>915</ymin>
			<xmax>592</xmax>
			<ymax>1022</ymax>
		</bndbox>
	</object>
<object>
		<name>/m/09j2d</name>
		<truncated>1</truncated>
		<bndbox>
			<xmin>667</xmin>
			<ymin>508</ymin>
			<xmax>1022</xmax>
			<ymax>967</ymax>
		</bndbox>
	</object>
<object>
		<name>/m/09j2d</name>
		<truncated>0</truncated>
		<bndbox>
			<xmin>674</xmin>
			<ymin>341</ymin>
			<xmax>813</xmax>
			<ymax>580</ymax>
		</bndbox>
	</object>
<object>
		<name>/m/0dzct</name>
		<truncated>0</truncated>
		<bndbox>
			<xmin>706</xmin>
			<ymin>309</ymin>
			<xmax>736</xmax>
			<ymax>353</ymax>
		</bndbox>
	</object>
<object>
		<name>/m/0dzct</name>
		<truncated>1</truncated>
		<bndbox>
			<xmin>998</xmin>
			<ymin>361</ymin>
			<xmax>1022</xmax>
			<ymax>438</ymax>
		</bndbox>
	</object>

</annotation>