<annotation>
	<folder>VOC2007</folder>
	<filename>e2561105f9bc876c.jpg</filename>
	<source>
		<database>OpenImagese</database>
		<annotation></annotation>
		<image></image>
		<flickrid></flickrid>
	</source>
	<owner>
		<flickrid></flickrid>
		<name></name>
	</owner>
	<size>
		<width>612</width>
		<height>1024</height>
		<depth>3</depth>
	</size>
	<segmented>0</segmented>
<object>
		<name>/m/01g317</name>
		<truncated>0</truncated>
		<bndbox>
			<xmin>39</xmin>
			<ymin>114</ymin>
			<xmax>384</xmax>
			<ymax>996</ymax>
		</bndbox>
	</object>
<object>
		<name>/m/09j2d</name>
		<truncated>1</truncated>
		<bndbox>
			<xmin>35</xmin>
			<ymin>186</ymin>
			<xmax>369</xmax>
			<ymax>988</ymax>
		</bndbox>
	</object>
<object>
		<name>/m/0hg7b</name>
		<truncated>0</truncated>
		<bndbox>
			<xmin>375</xmin>
			<ymin>325</ymin>
			<xmax>466</xmax>
			<ymax>487</ymax>
		</bndbox>
	</object>
<object>
		<name>/m/0dzct</name>
		<truncated>0</truncated>
		<bndbox>
			<xmin>158</xmin>
			<ymin>170</ymin>
			<xmax>266</xmax>
			<ymax>336</ymax>
		</bndbox>
	</object>

</annotation>