<annotation>
	<folder>VOC2007</folder>
	<filename>e3970c9067c5ff4c.jpg</filename>
	<source>
		<database>OpenImagese</database>
		<annotation></annotation>
		<image></image>
		<flickrid></flickrid>
	</source>
	<owner>
		<flickrid></flickrid>
		<name></name>
	</owner>
	<size>
		<width>1024</width>
		<height>768</height>
		<depth>3</depth>
	</size>
	<segmented>0</segmented>
<object>
		<name>/m/01bfm9</name>
		<truncated>1</truncated>
		<bndbox>
			<xmin>0</xmin>
			<ymin>413</ymin>
			<xmax>34</xmax>
			<ymax>487</ymax>
		</bndbox>
	</object>
<object>
		<name>/m/01bfm9</name>
		<truncated>0</truncated>
		<bndbox>
			<xmin>644</xmin>
			<ymin>191</ymin>
			<xmax>684</xmax>
			<ymax>219</ymax>
		</bndbox>
	</object>
<object>
		<name>/m/03bt1vf</name>
		<truncated>1</truncated>
		<bndbox>
			<xmin>0</xmin>
			<ymin>107</ymin>
			<xmax>217</xmax>
			<ymax>767</ymax>
		</bndbox>
	</object>
<object>
		<name>/m/04yx4</name>
		<truncated>0</truncated>
		<bndbox>
			<xmin>200</xmin>
			<ymin>69</ymin>
			<xmax>572</xmax>
			<ymax>631</ymax>
		</bndbox>
	</object>
<object>
		<name>/m/04yx4</name>
		<truncated>0</truncated>
		<bndbox>
			<xmin>568</xmin>
			<ymin>177</ymin>
			<xmax>604</xmax>
			<ymax>214</ymax>
		</bndbox>
	</object>
<object>
		<name>/m/05r655</name>
		<truncated>1</truncated>
		<bndbox>
			<xmin>0</xmin>
			<ymin>104</ymin>
			<xmax>216</xmax>
			<ymax>767</ymax>
		</bndbox>
	</object>
<object>
		<name>/m/05r655</name>
		<truncated>1</truncated>
		<bndbox>
			<xmin>0</xmin>
			<ymin>202</ymin>
			<xmax>115</xmax>
			<ymax>618</ymax>
		</bndbox>
	</object>
<object>
		<name>/m/05r655</name>
		<truncated>0</truncated>
		<bndbox>
			<xmin>646</xmin>
			<ymin>153</ymin>
			<xmax>674</xmax>
			<ymax>258</ymax>
		</bndbox>
	</object>
<object>
		<name>/m/09j5n</name>
		<truncated>1</truncated>
		<bndbox>
			<xmin>0</xmin>
			<ymin>565</ymin>
			<xmax>46</xmax>
			<ymax>621</ymax>
		</bndbox>
	</object>
<object>
		<name>/m/09j5n</name>
		<truncated>0</truncated>
		<bndbox>
			<xmin>103</xmin>
			<ymin>690</ymin>
			<xmax>214</xmax>
			<ymax>755</ymax>
		</bndbox>
	</object>
<object>
		<name>/m/09j5n</name>
		<truncated>0</truncated>
		<bndbox>
			<xmin>104</xmin>
			<ymin>585</ymin>
			<xmax>122</xmax>
			<ymax>600</ymax>
		</bndbox>
	</object>
<object>
		<name>/m/09j5n</name>
		<truncated>1</truncated>
		<bndbox>
			<xmin>107</xmin>
			<ymin>750</ymin>
			<xmax>180</xmax>
			<ymax>767</ymax>
		</bndbox>
	</object>
<object>
		<name>/m/09j5n</name>
		<truncated>0</truncated>
		<bndbox>
			<xmin>649</xmin>
			<ymin>238</ymin>
			<xmax>663</xmax>
			<ymax>255</ymax>
		</bndbox>
	</object>

</annotation>