<annotation>
	<folder>VOC2007</folder>
	<filename>e3c73f27c3c3693f.jpg</filename>
	<source>
		<database>OpenImagese</database>
		<annotation></annotation>
		<image></image>
		<flickrid></flickrid>
	</source>
	<owner>
		<flickrid></flickrid>
		<name></name>
	</owner>
	<size>
		<width>768</width>
		<height>1024</height>
		<depth>3</depth>
	</size>
	<segmented>0</segmented>
<object>
		<name>/m/07j7r</name>
		<truncated>0</truncated>
		<bndbox>
			<xmin>134</xmin>
			<ymin>743</ymin>
			<xmax>261</xmax>
			<ymax>853</ymax>
		</bndbox>
	</object>
<object>
		<name>/m/07j7r</name>
		<truncated>1</truncated>
		<bndbox>
			<xmin>730</xmin>
			<ymin>529</ymin>
			<xmax>767</xmax>
			<ymax>751</ymax>
		</bndbox>
	</object>

</annotation>