<annotation>
	<folder>VOC2007</folder>
	<filename>e4a9d4e9b42b8021.jpg</filename>
	<source>
		<database>OpenImagese</database>
		<annotation></annotation>
		<image></image>
		<flickrid></flickrid>
	</source>
	<owner>
		<flickrid></flickrid>
		<name></name>
	</owner>
	<size>
		<width>1024</width>
		<height>768</height>
		<depth>3</depth>
	</size>
	<segmented>0</segmented>
<object>
		<name>/m/04yx4</name>
		<truncated>1</truncated>
		<bndbox>
			<xmin>39</xmin>
			<ymin>0</ymin>
			<xmax>138</xmax>
			<ymax>60</ymax>
		</bndbox>
	</object>
<object>
		<name>/m/04yx4</name>
		<truncated>1</truncated>
		<bndbox>
			<xmin>480</xmin>
			<ymin>190</ymin>
			<xmax>680</xmax>
			<ymax>522</ymax>
		</bndbox>
	</object>
<object>
		<name>/m/04yx4</name>
		<truncated>1</truncated>
		<bndbox>
			<xmin>641</xmin>
			<ymin>566</ymin>
			<xmax>869</xmax>
			<ymax>767</ymax>
		</bndbox>
	</object>
<object>
		<name>/m/04yx4</name>
		<truncated>1</truncated>
		<bndbox>
			<xmin>706</xmin>
			<ymin>0</ymin>
			<xmax>848</xmax>
			<ymax>265</ymax>
		</bndbox>
	</object>
<object>
		<name>/m/09j2d</name>
		<truncated>1</truncated>
		<bndbox>
			<xmin>37</xmin>
			<ymin>0</ymin>
			<xmax>112</xmax>
			<ymax>37</ymax>
		</bndbox>
	</object>
<object>
		<name>/m/09j2d</name>
		<truncated>0</truncated>
		<bndbox>
			<xmin>570</xmin>
			<ymin>254</ymin>
			<xmax>664</xmax>
			<ymax>423</ymax>
		</bndbox>
	</object>
<object>
		<name>/m/09j2d</name>
		<truncated>1</truncated>
		<bndbox>
			<xmin>678</xmin>
			<ymin>639</ymin>
			<xmax>856</xmax>
			<ymax>763</ymax>
		</bndbox>
	</object>
<object>
		<name>/m/09j2d</name>
		<truncated>1</truncated>
		<bndbox>
			<xmin>721</xmin>
			<ymin>17</ymin>
			<xmax>821</xmax>
			<ymax>236</ymax>
		</bndbox>
	</object>
<object>
		<name>/m/09j2d</name>
		<truncated>1</truncated>
		<bndbox>
			<xmin>979</xmin>
			<ymin>118</ymin>
			<xmax>1023</xmax>
			<ymax>313</ymax>
		</bndbox>
	</object>
<object>
		<name>/m/0cnyhnx</name>
		<truncated>0</truncated>
		<bndbox>
			<xmin>248</xmin>
			<ymin>318</ymin>
			<xmax>574</xmax>
			<ymax>516</ymax>
		</bndbox>
	</object>

</annotation>