<annotation>
	<folder>VOC2007</folder>
	<filename>e70c3ecdc182ef03.jpg</filename>
	<source>
		<database>OpenImagese</database>
		<annotation></annotation>
		<image></image>
		<flickrid></flickrid>
	</source>
	<owner>
		<flickrid></flickrid>
		<name></name>
	</owner>
	<size>
		<width>768</width>
		<height>971</height>
		<depth>3</depth>
	</size>
	<segmented>0</segmented>
<object>
		<name>/m/0hg7b</name>
		<truncated>0</truncated>
		<bndbox>
			<xmin>376</xmin>
			<ymin>194</ymin>
			<xmax>643</xmax>
			<ymax>264</ymax>
		</bndbox>
	</object>

</annotation>