<annotation>
	<folder>VOC2007</folder>
	<filename>e7503752c37f13af.jpg</filename>
	<source>
		<database>OpenImagese</database>
		<annotation></annotation>
		<image></image>
		<flickrid></flickrid>
	</source>
	<owner>
		<flickrid></flickrid>
		<name></name>
	</owner>
	<size>
		<width>1024</width>
		<height>683</height>
		<depth>3</depth>
	</size>
	<segmented>0</segmented>
<object>
		<name>/m/01bl7v</name>
		<truncated>1</truncated>
		<bndbox>
			<xmin>170</xmin>
			<ymin>185</ymin>
			<xmax>324</xmax>
			<ymax>682</ymax>
		</bndbox>
	</object>
<object>
		<name>/m/01bl7v</name>
		<truncated>1</truncated>
		<bndbox>
			<xmin>236</xmin>
			<ymin>246</ymin>
			<xmax>400</xmax>
			<ymax>682</ymax>
		</bndbox>
	</object>
<object>
		<name>/m/01bl7v</name>
		<truncated>0</truncated>
		<bndbox>
			<xmin>264</xmin>
			<ymin>205</ymin>
			<xmax>346</xmax>
			<ymax>345</ymax>
		</bndbox>
	</object>
<object>
		<name>/m/01bl7v</name>
		<truncated>1</truncated>
		<bndbox>
			<xmin>294</xmin>
			<ymin>233</ymin>
			<xmax>483</xmax>
			<ymax>682</ymax>
		</bndbox>
	</object>
<object>
		<name>/m/01bl7v</name>
		<truncated>1</truncated>
		<bndbox>
			<xmin>449</xmin>
			<ymin>157</ymin>
			<xmax>600</xmax>
			<ymax>682</ymax>
		</bndbox>
	</object>
<object>
		<name>/m/01bl7v</name>
		<truncated>1</truncated>
		<bndbox>
			<xmin>668</xmin>
			<ymin>226</ymin>
			<xmax>875</xmax>
			<ymax>682</ymax>
		</bndbox>
	</object>

</annotation>