<annotation>
	<folder>VOC2007</folder>
	<filename>e85c3141882a8baf.jpg</filename>
	<source>
		<database>OpenImagese</database>
		<annotation></annotation>
		<image></image>
		<flickrid></flickrid>
	</source>
	<owner>
		<flickrid></flickrid>
		<name></name>
	</owner>
	<size>
		<width>617</width>
		<height>1024</height>
		<depth>3</depth>
	</size>
	<segmented>0</segmented>
<object>
		<name>/m/01bl7v</name>
		<truncated>0</truncated>
		<bndbox>
			<xmin>117</xmin>
			<ymin>428</ymin>
			<xmax>367</xmax>
			<ymax>995</ymax>
		</bndbox>
	</object>
<object>
		<name>/m/09j2d</name>
		<truncated>0</truncated>
		<bndbox>
			<xmin>131</xmin>
			<ymin>486</ymin>
			<xmax>357</xmax>
			<ymax>955</ymax>
		</bndbox>
	</object>

</annotation>