<annotation>
	<folder>VOC2007</folder>
	<filename>ea3e48fe8ad54774.jpg</filename>
	<source>
		<database>OpenImagese</database>
		<annotation></annotation>
		<image></image>
		<flickrid></flickrid>
	</source>
	<owner>
		<flickrid></flickrid>
		<name></name>
	</owner>
	<size>
		<width>1024</width>
		<height>768</height>
		<depth>3</depth>
	</size>
	<segmented>0</segmented>
<object>
		<name>/m/01599</name>
		<truncated>0</truncated>
		<bndbox>
			<xmin>300</xmin>
			<ymin>588</ymin>
			<xmax>401</xmax>
			<ymax>744</ymax>
		</bndbox>
	</object>
<object>
		<name>/m/01599</name>
		<truncated>0</truncated>
		<bndbox>
			<xmin>362</xmin>
			<ymin>240</ymin>
			<xmax>421</xmax>
			<ymax>333</ymax>
		</bndbox>
	</object>
<object>
		<name>/m/01599</name>
		<truncated>0</truncated>
		<bndbox>
			<xmin>380</xmin>
			<ymin>263</ymin>
			<xmax>465</xmax>
			<ymax>439</ymax>
		</bndbox>
	</object>
<object>
		<name>/m/01599</name>
		<truncated>0</truncated>
		<bndbox>
			<xmin>467</xmin>
			<ymin>252</ymin>
			<xmax>549</xmax>
			<ymax>439</ymax>
		</bndbox>
	</object>
<object>
		<name>/m/01599</name>
		<truncated>0</truncated>
		<bndbox>
			<xmin>492</xmin>
			<ymin>528</ymin>
			<xmax>561</xmax>
			<ymax>676</ymax>
		</bndbox>
	</object>
<object>
		<name>/m/01g317</name>
		<truncated>1</truncated>
		<bndbox>
			<xmin>0</xmin>
			<ymin>130</ymin>
			<xmax>449</xmax>
			<ymax>760</ymax>
		</bndbox>
	</object>
<object>
		<name>/m/01g317</name>
		<truncated>0</truncated>
		<bndbox>
			<xmin>231</xmin>
			<ymin>166</ymin>
			<xmax>320</xmax>
			<ymax>371</ymax>
		</bndbox>
	</object>
<object>
		<name>/m/01g317</name>
		<truncated>0</truncated>
		<bndbox>
			<xmin>273</xmin>
			<ymin>138</ymin>
			<xmax>385</xmax>
			<ymax>286</ymax>
		</bndbox>
	</object>
<object>
		<name>/m/01g317</name>
		<truncated>0</truncated>
		<bndbox>
			<xmin>289</xmin>
			<ymin>133</ymin>
			<xmax>558</xmax>
			<ymax>559</ymax>
		</bndbox>
	</object>
<object>
		<name>/m/01g317</name>
		<truncated>1</truncated>
		<bndbox>
			<xmin>483</xmin>
			<ymin>107</ymin>
			<xmax>1022</xmax>
			<ymax>767</ymax>
		</bndbox>
	</object>
<object>
		<name>/m/081qc</name>
		<truncated>0</truncated>
		<bndbox>
			<xmin>378</xmin>
			<ymin>282</ymin>
			<xmax>433</xmax>
			<ymax>315</ymax>
		</bndbox>
	</object>
<object>
		<name>/m/081qc</name>
		<truncated>0</truncated>
		<bndbox>
			<xmin>384</xmin>
			<ymin>303</ymin>
			<xmax>455</xmax>
			<ymax>341</ymax>
		</bndbox>
	</object>
<object>
		<name>/m/081qc</name>
		<truncated>0</truncated>
		<bndbox>
			<xmin>471</xmin>
			<ymin>297</ymin>
			<xmax>540</xmax>
			<ymax>359</ymax>
		</bndbox>
	</object>

</annotation>