<annotation>
	<folder>VOC2007</folder>
	<filename>ec55d1ac4cd22217.jpg</filename>
	<source>
		<database>OpenImagese</database>
		<annotation></annotation>
		<image></image>
		<flickrid></flickrid>
	</source>
	<owner>
		<flickrid></flickrid>
		<name></name>
	</owner>
	<size>
		<width>1024</width>
		<height>768</height>
		<depth>3</depth>
	</size>
	<segmented>0</segmented>
<object>
		<name>/m/01g317</name>
		<truncated>0</truncated>
		<bndbox>
			<xmin>5</xmin>
			<ymin>233</ymin>
			<xmax>78</xmax>
			<ymax>488</ymax>
		</bndbox>
	</object>
<object>
		<name>/m/01g317</name>
		<truncated>0</truncated>
		<bndbox>
			<xmin>96</xmin>
			<ymin>262</ymin>
			<xmax>144</xmax>
			<ymax>468</ymax>
		</bndbox>
	</object>
<object>
		<name>/m/01g317</name>
		<truncated>0</truncated>
		<bndbox>
			<xmin>146</xmin>
			<ymin>260</ymin>
			<xmax>243</xmax>
			<ymax>409</ymax>
		</bndbox>
	</object>
<object>
		<name>/m/01g317</name>
		<truncated>0</truncated>
		<bndbox>
			<xmin>214</xmin>
			<ymin>253</ymin>
			<xmax>263</xmax>
			<ymax>380</ymax>
		</bndbox>
	</object>
<object>
		<name>/m/01g317</name>
		<truncated>0</truncated>
		<bndbox>
			<xmin>250</xmin>
			<ymin>281</ymin>
			<xmax>318</xmax>
			<ymax>389</ymax>
		</bndbox>
	</object>
<object>
		<name>/m/01g317</name>
		<truncated>0</truncated>
		<bndbox>
			<xmin>354</xmin>
			<ymin>267</ymin>
			<xmax>443</xmax>
			<ymax>348</ymax>
		</bndbox>
	</object>
<object>
		<name>/m/01g317</name>
		<truncated>0</truncated>
		<bndbox>
			<xmin>574</xmin>
			<ymin>261</ymin>
			<xmax>628</xmax>
			<ymax>338</ymax>
		</bndbox>
	</object>
<object>
		<name>/m/0k4j</name>
		<truncated>0</truncated>
		<bndbox>
			<xmin>40</xmin>
			<ymin>193</ymin>
			<xmax>968</xmax>
			<ymax>702</ymax>
		</bndbox>
	</object>

</annotation>