<annotation>
	<folder>VOC2007</folder>
	<filename>ecd326fe4ec59541.jpg</filename>
	<source>
		<database>OpenImagese</database>
		<annotation></annotation>
		<image></image>
		<flickrid></flickrid>
	</source>
	<owner>
		<flickrid></flickrid>
		<name></name>
	</owner>
	<size>
		<width>1024</width>
		<height>768</height>
		<depth>3</depth>
	</size>
	<segmented>0</segmented>
<object>
		<name>/m/03bt1vf</name>
		<truncated>0</truncated>
		<bndbox>
			<xmin>202</xmin>
			<ymin>425</ymin>
			<xmax>321</xmax>
			<ymax>743</ymax>
		</bndbox>
	</object>
<object>
		<name>/m/04yx4</name>
		<truncated>0</truncated>
		<bndbox>
			<xmin>557</xmin>
			<ymin>178</ymin>
			<xmax>673</xmax>
			<ymax>485</ymax>
		</bndbox>
	</object>
<object>
		<name>/m/09j2d</name>
		<truncated>0</truncated>
		<bndbox>
			<xmin>200</xmin>
			<ymin>455</ymin>
			<xmax>301</xmax>
			<ymax>725</ymax>
		</bndbox>
	</object>
<object>
		<name>/m/03bt1vf</name>
		<truncated>0</truncated>
		<bndbox>
			<xmin>273</xmin>
			<ymin>413</ymin>
			<xmax>296</xmax>
			<ymax>462</ymax>
		</bndbox>
	</object>
<object>
		<name>/m/03bt1vf</name>
		<truncated>0</truncated>
		<bndbox>
			<xmin>296</xmin>
			<ymin>409</ymin>
			<xmax>318</xmax>
			<ymax>481</ymax>
		</bndbox>
	</object>
<object>
		<name>/m/03bt1vf</name>
		<truncated>0</truncated>
		<bndbox>
			<xmin>320</xmin>
			<ymin>480</ymin>
			<xmax>356</xmax>
			<ymax>522</ymax>
		</bndbox>
	</object>
<object>
		<name>/m/03bt1vf</name>
		<truncated>0</truncated>
		<bndbox>
			<xmin>408</xmin>
			<ymin>476</ymin>
			<xmax>441</xmax>
			<ymax>528</ymax>
		</bndbox>
	</object>
<object>
		<name>/m/03bt1vf</name>
		<truncated>0</truncated>
		<bndbox>
			<xmin>818</xmin>
			<ymin>453</ymin>
			<xmax>842</xmax>
			<ymax>508</ymax>
		</bndbox>
	</object>
<object>
		<name>/m/04yx4</name>
		<truncated>0</truncated>
		<bndbox>
			<xmin>58</xmin>
			<ymin>414</ymin>
			<xmax>92</xmax>
			<ymax>464</ymax>
		</bndbox>
	</object>
<object>
		<name>/m/04yx4</name>
		<truncated>0</truncated>
		<bndbox>
			<xmin>213</xmin>
			<ymin>395</ymin>
			<xmax>270</xmax>
			<ymax>624</ymax>
		</bndbox>
	</object>
<object>
		<name>/m/04yx4</name>
		<truncated>0</truncated>
		<bndbox>
			<xmin>504</xmin>
			<ymin>453</ymin>
			<xmax>557</xmax>
			<ymax>579</ymax>
		</bndbox>
	</object>
<object>
		<name>/m/04yx4</name>
		<truncated>0</truncated>
		<bndbox>
			<xmin>645</xmin>
			<ymin>442</ymin>
			<xmax>672</xmax>
			<ymax>488</ymax>
		</bndbox>
	</object>
<object>
		<name>/m/07j7r</name>
		<truncated>1</truncated>
		<bndbox>
			<xmin>0</xmin>
			<ymin>0</ymin>
			<xmax>828</xmax>
			<ymax>275</ymax>
		</bndbox>
	</object>
<object>
		<name>/m/07j7r</name>
		<truncated>1</truncated>
		<bndbox>
			<xmin>0</xmin>
			<ymin>0</ymin>
			<xmax>1004</xmax>
			<ymax>138</ymax>
		</bndbox>
	</object>
<object>
		<name>/m/07j7r</name>
		<truncated>1</truncated>
		<bndbox>
			<xmin>633</xmin>
			<ymin>15</ymin>
			<xmax>1023</xmax>
			<ymax>614</ymax>
		</bndbox>
	</object>
<object>
		<name>/m/09j2d</name>
		<truncated>0</truncated>
		<bndbox>
			<xmin>59</xmin>
			<ymin>426</ymin>
			<xmax>92</xmax>
			<ymax>462</ymax>
		</bndbox>
	</object>
<object>
		<name>/m/09j2d</name>
		<truncated>0</truncated>
		<bndbox>
			<xmin>74</xmin>
			<ymin>423</ymin>
			<xmax>112</xmax>
			<ymax>472</ymax>
		</bndbox>
	</object>
<object>
		<name>/m/09j2d</name>
		<truncated>0</truncated>
		<bndbox>
			<xmin>165</xmin>
			<ymin>426</ymin>
			<xmax>183</xmax>
			<ymax>448</ymax>
		</bndbox>
	</object>
<object>
		<name>/m/09j2d</name>
		<truncated>0</truncated>
		<bndbox>
			<xmin>215</xmin>
			<ymin>427</ymin>
			<xmax>268</xmax>
			<ymax>616</ymax>
		</bndbox>
	</object>
<object>
		<name>/m/09j2d</name>
		<truncated>0</truncated>
		<bndbox>
			<xmin>297</xmin>
			<ymin>494</ymin>
			<xmax>355</xmax>
			<ymax>587</ymax>
		</bndbox>
	</object>
<object>
		<name>/m/09j2d</name>
		<truncated>0</truncated>
		<bndbox>
			<xmin>305</xmin>
			<ymin>419</ymin>
			<xmax>326</xmax>
			<ymax>484</ymax>
		</bndbox>
	</object>
<object>
		<name>/m/09j2d</name>
		<truncated>0</truncated>
		<bndbox>
			<xmin>327</xmin>
			<ymin>439</ymin>
			<xmax>358</xmax>
			<ymax>480</ymax>
		</bndbox>
	</object>
<object>
		<name>/m/09j2d</name>
		<truncated>0</truncated>
		<bndbox>
			<xmin>389</xmin>
			<ymin>444</ymin>
			<xmax>406</xmax>
			<ymax>478</ymax>
		</bndbox>
	</object>
<object>
		<name>/m/09j2d</name>
		<truncated>0</truncated>
		<bndbox>
			<xmin>412</xmin>
			<ymin>488</ymin>
			<xmax>440</xmax>
			<ymax>522</ymax>
		</bndbox>
	</object>
<object>
		<name>/m/09j2d</name>
		<truncated>0</truncated>
		<bndbox>
			<xmin>514</xmin>
			<ymin>463</ymin>
			<xmax>552</xmax>
			<ymax>541</ymax>
		</bndbox>
	</object>
<object>
		<name>/m/09j2d</name>
		<truncated>0</truncated>
		<bndbox>
			<xmin>641</xmin>
			<ymin>449</ymin>
			<xmax>670</xmax>
			<ymax>496</ymax>
		</bndbox>
	</object>
<object>
		<name>/m/0k4j</name>
		<truncated>1</truncated>
		<bndbox>
			<xmin>0</xmin>
			<ymin>482</ymin>
			<xmax>207</xmax>
			<ymax>752</ymax>
		</bndbox>
	</object>
<object>
		<name>/m/0k4j</name>
		<truncated>0</truncated>
		<bndbox>
			<xmin>615</xmin>
			<ymin>436</ymin>
			<xmax>750</xmax>
			<ymax>526</ymax>
		</bndbox>
	</object>

</annotation>