<annotation>
	<folder>VOC2007</folder>
	<filename>ed1cf9c29b8c33f7.jpg</filename>
	<source>
		<database>OpenImagese</database>
		<annotation></annotation>
		<image></image>
		<flickrid></flickrid>
	</source>
	<owner>
		<flickrid></flickrid>
		<name></name>
	</owner>
	<size>
		<width>1024</width>
		<height>768</height>
		<depth>3</depth>
	</size>
	<segmented>0</segmented>
<object>
		<name>/m/07j7r</name>
		<truncated>1</truncated>
		<bndbox>
			<xmin>481</xmin>
			<ymin>0</ymin>
			<xmax>931</xmax>
			<ymax>317</ymax>
		</bndbox>
	</object>
<object>
		<name>/m/07j7r</name>
		<truncated>1</truncated>
		<bndbox>
			<xmin>529</xmin>
			<ymin>256</ymin>
			<xmax>848</xmax>
			<ymax>704</ymax>
		</bndbox>
	</object>
<object>
		<name>/m/07j7r</name>
		<truncated>1</truncated>
		<bndbox>
			<xmin>609</xmin>
			<ymin>445</ymin>
			<xmax>1023</xmax>
			<ymax>767</ymax>
		</bndbox>
	</object>
<object>
		<name>/m/07j7r</name>
		<truncated>1</truncated>
		<bndbox>
			<xmin>647</xmin>
			<ymin>687</ymin>
			<xmax>896</xmax>
			<ymax>767</ymax>
		</bndbox>
	</object>

</annotation>