<annotation>
	<folder>VOC2007</folder>
	<filename>ee3aa47ec9d1a426.jpg</filename>
	<source>
		<database>OpenImagese</database>
		<annotation></annotation>
		<image></image>
		<flickrid></flickrid>
	</source>
	<owner>
		<flickrid></flickrid>
		<name></name>
	</owner>
	<size>
		<width>1024</width>
		<height>768</height>
		<depth>3</depth>
	</size>
	<segmented>0</segmented>
<object>
		<name>/m/04yx4</name>
		<truncated>0</truncated>
		<bndbox>
			<xmin>456</xmin>
			<ymin>90</ymin>
			<xmax>587</xmax>
			<ymax>328</ymax>
		</bndbox>
	</object>
<object>
		<name>/m/09j5n</name>
		<truncated>0</truncated>
		<bndbox>
			<xmin>460</xmin>
			<ymin>297</ymin>
			<xmax>494</xmax>
			<ymax>327</ymax>
		</bndbox>
	</object>
<object>
		<name>/m/09j5n</name>
		<truncated>0</truncated>
		<bndbox>
			<xmin>523</xmin>
			<ymin>291</ymin>
			<xmax>549</xmax>
			<ymax>309</ymax>
		</bndbox>
	</object>
<object>
		<name>/m/09j5n</name>
		<truncated>0</truncated>
		<bndbox>
			<xmin>545</xmin>
			<ymin>306</ymin>
			<xmax>588</xmax>
			<ymax>325</ymax>
		</bndbox>
	</object>
<object>
		<name>/m/09j5n</name>
		<truncated>0</truncated>
		<bndbox>
			<xmin>602</xmin>
			<ymin>285</ymin>
			<xmax>636</xmax>
			<ymax>307</ymax>
		</bndbox>
	</object>

</annotation>