<annotation>
	<folder>VOC2007</folder>
	<filename>eea891b4af126999.jpg</filename>
	<source>
		<database>OpenImagese</database>
		<annotation></annotation>
		<image></image>
		<flickrid></flickrid>
	</source>
	<owner>
		<flickrid></flickrid>
		<name></name>
	</owner>
	<size>
		<width>1024</width>
		<height>680</height>
		<depth>3</depth>
	</size>
	<segmented>0</segmented>
<object>
		<name>/m/03jm5</name>
		<truncated>0</truncated>
		<bndbox>
			<xmin>0</xmin>
			<ymin>33</ymin>
			<xmax>1024</xmax>
			<ymax>615</ymax>
		</bndbox>
	</object>
<object>
		<name>/m/04yx4</name>
		<truncated>1</truncated>
		<bndbox>
			<xmin>321</xmin>
			<ymin>351</ymin>
			<xmax>672</xmax>
			<ymax>633</ymax>
		</bndbox>
	</object>
<object>
		<name>/m/0jyfg</name>
		<truncated>0</truncated>
		<bndbox>
			<xmin>335</xmin>
			<ymin>449</ymin>
			<xmax>613</xmax>
			<ymax>555</ymax>
		</bndbox>
	</object>
<object>
		<name>/m/017ftj</name>
		<truncated>0</truncated>
		<bndbox>
			<xmin>369</xmin>
			<ymin>423</ymin>
			<xmax>598</xmax>
			<ymax>543</ymax>
		</bndbox>
	</object>
<object>
		<name>/m/02dl1y</name>
		<truncated>1</truncated>
		<bndbox>
			<xmin>289</xmin>
			<ymin>348</ymin>
			<xmax>650</xmax>
			<ymax>543</ymax>
		</bndbox>
	</object>
<object>
		<name>/m/02_n6y</name>
		<truncated>0</truncated>
		<bndbox>
			<xmin>366</xmin>
			<ymin>430</ymin>
			<xmax>592</xmax>
			<ymax>527</ymax>
		</bndbox>
	</object>
<object>
		<name>/m/0d4v4</name>
		<truncated>1</truncated>
		<bndbox>
			<xmin>0</xmin>
			<ymin>0</ymin>
			<xmax>204</xmax>
			<ymax>262</ymax>
		</bndbox>
	</object>
<object>
		<name>/m/0d4v4</name>
		<truncated>0</truncated>
		<bndbox>
			<xmin>29</xmin>
			<ymin>332</ymin>
			<xmax>199</xmax>
			<ymax>447</ymax>
		</bndbox>
	</object>
<object>
		<name>/m/0d4v4</name>
		<truncated>1</truncated>
		<bndbox>
			<xmin>279</xmin>
			<ymin>0</ymin>
			<xmax>666</xmax>
			<ymax>258</ymax>
		</bndbox>
	</object>
<object>
		<name>/m/0d4v4</name>
		<truncated>1</truncated>
		<bndbox>
			<xmin>739</xmin>
			<ymin>330</ymin>
			<xmax>1023</xmax>
			<ymax>437</ymax>
		</bndbox>
	</object>
<object>
		<name>/m/0d4v4</name>
		<truncated>1</truncated>
		<bndbox>
			<xmin>741</xmin>
			<ymin>0</ymin>
			<xmax>1022</xmax>
			<ymax>257</ymax>
		</bndbox>
	</object>
<object>
		<name>/m/0dzct</name>
		<truncated>1</truncated>
		<bndbox>
			<xmin>380</xmin>
			<ymin>431</ymin>
			<xmax>612</xmax>
			<ymax>614</ymax>
		</bndbox>
	</object>

</annotation>