<annotation>
	<folder>VOC2007</folder>
	<filename>ef10c5eb2d2a1c30.jpg</filename>
	<source>
		<database>OpenImagese</database>
		<annotation></annotation>
		<image></image>
		<flickrid></flickrid>
	</source>
	<owner>
		<flickrid></flickrid>
		<name></name>
	</owner>
	<size>
		<width>597</width>
		<height>1024</height>
		<depth>3</depth>
	</size>
	<segmented>0</segmented>
<object>
		<name>/m/0ch_cf</name>
		<truncated>0</truncated>
		<bndbox>
			<xmin>106</xmin>
			<ymin>466</ymin>
			<xmax>426</xmax>
			<ymax>560</ymax>
		</bndbox>
	</object>

</annotation>