<annotation>
	<folder>VOC2007</folder>
	<filename>efcee9ef2af42893.jpg</filename>
	<source>
		<database>OpenImagese</database>
		<annotation></annotation>
		<image></image>
		<flickrid></flickrid>
	</source>
	<owner>
		<flickrid></flickrid>
		<name></name>
	</owner>
	<size>
		<width>1024</width>
		<height>892</height>
		<depth>3</depth>
	</size>
	<segmented>0</segmented>
<object>
		<name>/m/01g317</name>
		<truncated>0</truncated>
		<bndbox>
			<xmin>326</xmin>
			<ymin>205</ymin>
			<xmax>444</xmax>
			<ymax>515</ymax>
		</bndbox>
	</object>
<object>
		<name>/m/01g317</name>
		<truncated>0</truncated>
		<bndbox>
			<xmin>493</xmin>
			<ymin>161</ymin>
			<xmax>965</xmax>
			<ymax>520</ymax>
		</bndbox>
	</object>

</annotation>